injects/__init__.py
injects/logs.py
injects/conditionals/__init__.py
injects/conditionals/base.py
injects/conditionals/context.py
injects/conditionals/typed.py
injects/conditionals/value.py
injects/core/__init__.py
injects/core/transformer.py
injects/insert/__init__.py
injects/insert/base.py
injects/insert/position.py
injects/insert/transform.py
injects/internal/__init__.py
injects/patterns/__init__.py
injects/patterns/base.py
injects/patterns/function.py
injects/patterns/operators.py
injects/patterns/variable.py
injects/transforms/__init__.py
injects/transforms/common.py
injects/transforms/modify.py
injects/utils/__init__.py
injects-0.1.0.dist-info/METADATA
injects-0.1.0.dist-info/WHEEL
injects-0.1.0.dist-info/top_level.txt
injects-0.1.0.dist-info/RECORD
