Metadata-Version: 2.4
Name: injects
Version: 0.1.0
Summary: Runtime dynamic code injection and manipulation via decorators
Author-email: Joel Yisrael <schizoprada@gmail.com>
License: MIT
Project-URL: Homepage, https://github.com/schizoprada/injects
Project-URL: Bug Reports, https://github.com/schizoprada/injects/issues
Project-URL: Source, https://github.com/schizoprada/injects
Classifier: Development Status :: 3 - Alpha
Classifier: Intended Audience :: Developers
Classifier: License :: OSI Approved :: MIT License
Classifier: Programming Language :: Python :: 3
Classifier: Programming Language :: Python :: 3.8
Classifier: Programming Language :: Python :: 3.9
Classifier: Programming Language :: Python :: 3.10
Classifier: Programming Language :: Python :: 3.11
Classifier: Topic :: Software Development :: Libraries :: Python Modules
Classifier: Topic :: Software Development :: Code Generators
Requires-Python: >=3.8
Requires-Dist: colorama>=0.4.4
Provides-Extra: dev
Requires-Dist: pytest>=7.0.0; extra == "dev"
Requires-Dist: black>=22.0.0; extra == "dev"
Requires-Dist: isort>=5.0.0; extra == "dev"
Requires-Dist: flake8>=5.0.0; extra == "dev"
Provides-Extra: test
Requires-Dist: pytest>=7.0.0; extra == "test"
